SC19013UNO/__init__.py
SC19013UNO/lineales.py
SC19013UNO/no_lineales.py
sc19013uno-1.0.0.dist-info/licenses/LICENSE
sc19013uno-1.0.0.dist-info/METADATA
sc19013uno-1.0.0.dist-info/WHEEL
sc19013uno-1.0.0.dist-info/top_level.txt
sc19013uno-1.0.0.dist-info/RECORD
