Metadata-Version: 2.4
Name: SC19013UNO
Version: 1.0.0
Summary: Librería de métodos numéricos para resolver sistemas de ecuaciones lineales y no lineales
Home-page: https://github.com/ACamposWeb/sc19013uno
Author: Luis Serpas
Author-email: sc19013@ues.edu.sv
Classifier: Programming Language :: Python :: 3
Classifier: License :: OSI Approved :: MIT License
Classifier: Operating System :: OS Independent
Requires-Python: >=3.6
License-File: LICENSE
Dynamic: author
Dynamic: author-email
Dynamic: classifier
Dynamic: description
Dynamic: description-content-type
Dynamic: home-page
Dynamic: license-file
Dynamic: requires-python
Dynamic: summary
